pyswot/__init__.py
pyswot/pyswot.py
pyswot/vendor/__init__.py
pyswot/vendor/domains.py
pyswot/vendor/free.py
pyswot/vendor/stoplist.py
pyswot/vendor/tlds.py
pyswot-0.5.0.dist-info/licenses/LICENSE
pyswot-0.5.0.dist-info/METADATA
pyswot-0.5.0.dist-info/WHEEL
pyswot-0.5.0.dist-info/top_level.txt
pyswot-0.5.0.dist-info/RECORD
