Metadata-Version: 2.4
Name: pyswot
Version: 0.5.0
Summary: Python wrapper for JetBrains/swot
Author: James Meakin
License: Apache-2.0
Project-URL: repository, https://github.com/DIAGNijmegen/rse-pyswot
Classifier: Development Status :: 3 - Alpha
Classifier: Intended Audience :: Developers
Requires-Python: <4.0,>=3.10
License-File: LICENSE
Dynamic: license-file
